ddsctrl/__init__.py
ddsctrl/constants.py
ddsctrl/ddsctrlui.py
ddsctrl/version.local.py
ddsctrl/version.py
ddsctrl-0.5.4.data/scripts/ddscontroller
ddsctrl-0.5.4.dist-info/licenses/LICENSE.txt
ddsctrl-0.5.4.dist-info/METADATA
ddsctrl-0.5.4.dist-info/WHEEL
ddsctrl-0.5.4.dist-info/top_level.txt
ddsctrl-0.5.4.dist-info/RECORD
