Metadata-Version: 2.4
Name: ddsctrl
Version: 0.5.4
Summary: ddscontroller allow basic handling of AD9912 and AD9915 DDS development board.
Home-page: https://gitlab.com/bendub/ddsctrl
Author: Benoit Dubois
Author-email: benoit.dubois@femto-engineering.fr
License: LGPL-3.0-or-later
Classifier: Development Status :: 4 - Beta
Classifier: Intended Audience :: Science/Research
Classifier: Natural Language :: English
Classifier: Operating System :: POSIX :: Linux
Classifier: Programming Language :: Python
Classifier: Topic :: Scientific/Engineering
License-File: LICENSE.txt
Requires-Dist: PyQt5
Requires-Dist: ad9xdds
Requires-Dist: signalslot
Dynamic: author
Dynamic: author-email
Dynamic: classifier
Dynamic: home-page
Dynamic: license
Dynamic: license-file
Dynamic: requires-dist
Dynamic: summary
